EandRFinal/__init__.py
EandRFinal/main.py
EandRFinal-0.1.6.dist-info/METADATA
EandRFinal-0.1.6.dist-info/WHEEL
EandRFinal-0.1.6.dist-info/top_level.txt
EandRFinal-0.1.6.dist-info/RECORD
